AUTHORS.rst
CONTRIBUTING.rst
LICENSE.txt
MANIFEST.in
README.rst
setup.cfg
setup.py
versioneer.py
dask_ndmeasure/__init__.py
dask_ndmeasure/_compat.py
dask_ndmeasure/_pycompat.py
dask_ndmeasure/_utils.py
dask_ndmeasure/_version.py
dask_ndmeasure.egg-info/PKG-INFO
dask_ndmeasure.egg-info/SOURCES.txt
dask_ndmeasure.egg-info/dependency_links.txt
dask_ndmeasure.egg-info/not-zip-safe
dask_ndmeasure.egg-info/requires.txt
dask_ndmeasure.egg-info/top_level.txt
docs/Makefile
docs/api.rst
docs/authors.rst
docs/conf.py
docs/contributing.rst
docs/history.rst
docs/index.rst
docs/installation.rst
docs/make.bat
docs/readme.rst
docs/usage.rst
tests/__init__.py
tests/test__compat.py
tests/test__pycompat.py
tests/test__utils.py
tests/test_core.py